{
    "ui": {
        "parent_name": "img_list_page",
        "ui_name": "met_m1156_3",
        "ui_page": "|img|",
        "ui_title": "图片模块列表页",
        "ui_description": "图片模块列表页",
        "ui_issue": "0",
        "ui_order": "1",
        "ui_version": "1.0",
        "ui_creater": "m1156",
        "ui_company": "m1156"
    },
    "config": [
        {
            "parent_name": "img_list_page",
            "ui_name": "met_m1156_3",
            "uip_type": "4",
            "uip_style": "0",
            "uip_select": "$M$开启$T$1$M$关闭$T$0",
            "uip_name": "ui_show",
            "uip_key": "ui_show",
            "uip_value": "",
            "uip_default": "1",
            "uip_title": "区块显示开关",
            "uip_description": "当前UI区块的开启关闭设置，关闭后可以在可视化编辑中开启",
            "uip_order": "0"
        },
        {
            "parent_name": "img_list_page",
            "ui_name": "met_m1156_3",
            "uip_type": "7",
            "uip_style": "0",
            "uip_select": "",
            "uip_name": "bgimg",
            "uip_key": "bgimg",
            "uip_value": "",
            "uip_default": "",
            "uip_title": "区块背景图",
            "uip_description": "背景图片建议尺寸：1920px * 1080px",
            "uip_order": "1"
        },
        {
            "parent_name": "img_list_page",
            "ui_name": "met_m1156_3",
            "uip_type": "9",
            "uip_style": "0",
            "uip_select": "",
            "uip_name": "bgcolor",
            "uip_key": "bgcolor",
            "uip_value": "",
            "uip_default": "",
            "uip_title": "区块背景色",
            "uip_description": "默认为网站背景颜色；如果添加了“区块背景图”则背景色会被遮挡。",
            "uip_order": "2"
        },
        {
            "parent_name": "img_list_page",
            "ui_name": "met_m1156_3",
            "uip_type": "9",
            "uip_style": "0",
            "uip_select": "",
            "uip_name": "titlecolor",
            "uip_key": "titlecolor-1",
            "uip_value": "",
            "uip_default": "",
            "uip_title": "标题文字颜色",
            "uip_description": "默认为模板主色调",
            "uip_order": "3"
        },
        {
            "parent_name": "img_list_page",
            "ui_name": "met_m1156_3",
            "uip_type": "9",
            "uip_style": "0",
            "uip_select": "",
            "uip_name": "hovercolor",
            "uip_key": "hovercolor-1",
            "uip_value": "",
            "uip_default": "",
            "uip_title": "区块配色调",
            "uip_description": "模板配色调",
            "uip_order": "5"
        },
        {
            "parent_name": "img_list_page",
            "ui_name": "met_m1156_3",
            "uip_type": "9",
            "uip_style": "0",
            "uip_select": "",
            "uip_name": "focuscolor",
            "uip_key": "focuscolor-1",
            "uip_value": "",
            "uip_default": "",
            "uip_title": "区块副色调",
            "uip_description": "区块中彩色区域中的文字颜色",
            "uip_order": "6"
        },
        {
            "parent_name": "img_list_page",
            "ui_name": "met_m1156_3",
            "uip_type": "9",
            "uip_style": "0",
            "uip_select": "",
            "uip_name": "pagebgcolor",
            "uip_key": "pagercolor",
            "uip_value": "",
            "uip_default": "",
            "uip_title": "翻页按钮背景色",
            "uip_description": "",
            "uip_order": "9"
        },
        {
            "parent_name": "img_list_page",
            "ui_name": "met_m1156_3",
            "uip_type": "9",
            "uip_style": "0",
            "uip_select": "",
            "uip_name": "pagetitlecolor",
            "uip_key": "pagetitlecolor",
            "uip_value": "",
            "uip_default": "",
            "uip_title": "翻页按钮字体颜色",
            "uip_description": "",
            "uip_order": "10"
        },
        {
            "parent_name": "img_list_page",
            "ui_name": "met_m1156_3",
            "uip_type": "9",
            "uip_style": "0",
            "uip_select": "",
            "uip_name": "pagehovercolor",
            "uip_key": "pagehovercolor",
            "uip_value": "",
            "uip_default": "",
            "uip_title": "翻页选中按钮字体颜色",
            "uip_description": "",
            "uip_order": "11"
        },
        {
            "parent_name": "img_list_page",
            "ui_name": "met_m1156_3",
            "uip_type": "9",
            "uip_style": "0",
            "uip_select": "",
            "uip_name": "pagebordercolor",
            "uip_key": "pagebordercolor",
            "uip_value": "",
            "uip_default": "",
            "uip_title": "翻页按钮线条颜色",
            "uip_description": "",
            "uip_order": "12"
        },
        {
            "parent_name": "img_list_page",
            "ui_name": "met_m1156_3",
            "uip_type": "2",
            "uip_style": "0",
            "uip_select": "",
            "uip_name": "looktext",
            "uip_key": "looktext",
            "uip_value": "",
            "uip_default": "浏览",
            "uip_title": "按钮文字",
            "uip_description": "",
            "uip_order": "13"
        },
        {
            "parent_name": "img_list_page",
            "ui_name": "met_m1156_3",
            "uip_type": "9",
            "uip_style": "0",
            "uip_select": "",
            "uip_name": "looktitlecolor",
            "uip_key": "looktitlecolor",
            "uip_value": "",
            "uip_default": "",
            "uip_title": "按钮文字颜色",
            "uip_description": "",
            "uip_order": "14"
        },
        {
            "parent_name": "img_list_page",
            "ui_name": "met_m1156_3",
            "uip_type": "9",
            "uip_style": "0",
            "uip_select": "",
            "uip_name": "lookbordercolor",
            "uip_key": "lookbordercolor",
            "uip_value": "",
            "uip_default": "",
            "uip_title": "按钮线条颜色",
            "uip_description": "",
            "uip_order": "15"
        },
        {
            "parent_name": "img_list_page",
            "ui_name": "met_m1156_3",
            "uip_type": "4",
            "uip_style": "0",
            "uip_select": "$M$开启$T$1$M$关闭$T$0",
            "uip_name": "full",
            "uip_key": "full",
            "uip_value": "",
            "uip_default": "1",
            "uip_title": "全屏宽显示",
            "uip_description": "",
            "uip_order": "17"
        },
        {
            "parent_name": "img_list_page",
            "ui_name": "met_m1156_3",
            "uip_type": "2",
            "uip_style": "0",
            "uip_select": "",
            "uip_name": "blocksxlg",
            "uip_key": "columnlg",
            "uip_value": "",
            "uip_default": "4",
            "uip_title": "大尺寸电脑显示列数",
            "uip_description": "大尺寸电脑：浏览器宽度大于1600像素",
            "uip_order": "18"
        },
        {
            "parent_name": "img_list_page",
            "ui_name": "met_m1156_3",
            "uip_type": "2",
            "uip_style": "0",
            "uip_select": "",
            "uip_name": "blocksmd",
            "uip_key": "columnmd",
            "uip_value": "",
            "uip_default": "4",
            "uip_title": "普通电脑显示列数",
            "uip_description": "普通电脑：浏览器宽度大于992像素小于1600像素",
            "uip_order": "19"
        },
        {
            "parent_name": "img_list_page",
            "ui_name": "met_m1156_3",
            "uip_type": "2",
            "uip_style": "0",
            "uip_select": "",
            "uip_name": "blockssm",
            "uip_key": "columnsm",
            "uip_value": "",
            "uip_default": "2",
            "uip_title": "平板显示列数",
            "uip_description": "平板：浏览器宽度大于768像素小于992像素",
            "uip_order": "20"
        },
        {
            "parent_name": "img_list_page",
            "ui_name": "met_m1156_3",
            "uip_type": "2",
            "uip_style": "0",
            "uip_select": "",
            "uip_name": "blocksxs",
            "uip_key": "columnxs",
            "uip_value": "",
            "uip_default": "2",
            "uip_title": "手机显示列数",
            "uip_description": "手机：浏览器宽度小于768像素",
            "uip_order": "21"
        }
    ]
}